cspy/__init__.py
cspy/__main__.py
cspy/interpreter.py
cspy/lexer.py
cspy/nodes.py
cspy/parser.py
cspy/py.typed
cspy/tokens.py
apcspy-0.1.2.dist-info/WHEEL
apcspy-0.1.2.dist-info/entry_points.txt
apcspy-0.1.2.dist-info/METADATA
apcspy-0.1.2.dist-info/RECORD
