Metadata-Version: 2.3
Name: APCSPy
Version: 0.1.2
Summary: AP CSP Pseudo-code Interpreter
Author: Edoc Li
Author-email: Edoc Li <123019149+edocli@users.noreply.github.com>
Requires-Python: >=3.10
